# 编译期

编译器将源代码翻译为机器能识别的代码，java为编译为jvm认识的字节码文件。 

# 运行期

指java代码的运行过程。 （加载--验证--准备--解析--初始化）Java虚拟机分配内存，解释执行字节码文件。 

# 区别

* **方法重载是在编译时执行的** 

  ```java
  public class Test{
      
      public void test1（Parnet parnet）{
          System.out.println("do parnet");
      }
      public void test1(Child child){
          System.out.println("do child");
      }
      public static void main(String[] args){
            
          Parnet parnet = new Child();
          new Test().test1(parnet);
      }
  }
  其中 child是parnet的子类。
  输出结果为？
  do parnet
  
  为什么？  因为调用test1（parnet） 在编译期就确定了 parnet是Parnet类型的 所以会执行Parnet的输出
  看一下编译后的内容：
   public void tee1();
      descriptor: ()V
      flags: ACC_PUBLIC
      Code:
        stack=2, locals=2, args_size=1
           0: new           #29                 // class com/sprucetec/price/research/crawler/ApiTest$Child
           3: dup
           4: invokespecial #30                 // Method com/sprucetec/price/research/crawler/ApiTest$Child."<init>":()V
           7: astore_1
           8: aload_0
           9: aload_1
          10: invokevirtual #31                 // Method tt:(Lcom/sprucetec/price/research/crawler/ApiTest$Parnet;)V
          13: return
        LineNumberTable:
          line 74: 0
          line 75: 8
          line 76: 13
        LocalVariableTable:
          Start  Length  Slot  Name   Signature
              0      14     0  this   Lcom/sprucetec/price/research/crawler/ApiTest;
              8       6     1    pp   Lcom/sprucetec/price/research/crawler/ApiTest$Parnet;
      RuntimeVisibleAnnotations:
        0: #65()
            
    编译时就已经确定了调用的为Method tt:(Lcom/sprucetec/price/research/crawler/ApiTest$Parnet;)V
  ```

* **方法的重写是在运行时进行的** 

* **泛型(类型检测)，这个发生在编译时。**

* **注解。注解即有可能是运行时也有可能是编译时。**

* **异常。异常即有可能是运行时异常，也有可能是编译时异常。** 

* **继承：继承是编译时执行的** 

* **代理(delegate)：也称动态代理，是在运行时执行。** 



# 例子

## 例子1

```java
public class Test{
    static final int a = 20;
    static final int b = 10;
    static int c = 20;
    static int d = 10;
    
    public static void main(String[] args){
        int num1 = a * b;
        int num2 = c * d;
    }
}

在编译期num1 和 num2  有什么区别?
```

> java编译期时会做一些优化，包括如果是两个常量做运算，那么结果是可以确定的，所以在编译期就会直接计算出结果。

```java
编译期就回是这样：
  public static void main(String[] args){
        int num1 =200;
        int num2 = c * d;
    }
```





